AUTHORS.md
CONTRIBUTORS.md
LICENSE.md
MANIFEST.in
README.rst
meson.build
meson_options.txt
setup.cfg
setup.py
doc/source/conf.py
doc/source/description.rst
doc/source/index.rst
doc/source/limits.rst
doc/source/links.rst
doc/source/objectives.rst
doc/source/roadmap.rst
doc/source/api/_index.rst
doc/source/api/dataloader.rst
doc/source/api/dataset.rst
doc/source/api/operations.rst
doc/source/api/utils.rst
doc/source/contribution/_index.rst
doc/source/contribution/contributing_changes.rst
doc/source/contribution/submitting_bugs.rst
doc/source/datasets/list.rst
doc/source/examples/_index.rst
doc/source/examples/imagenet_example.rst
include/meson.build
include/benzina/attribute.h
include/benzina/benzina-old.h
include/benzina/benzina.h
include/benzina/bits.h
include/benzina/config.h
include/benzina/endian.h
include/benzina/inline.h
include/benzina/intops.h
include/benzina/meson.build
include/benzina/ptrops.h
include/benzina/siphash.h
include/benzina/version.h
include/benzina/visibility.h
include/benzina/bcachefs/bcachefs-ops.h
include/benzina/bcachefs/bcachefs-types.h
include/benzina/bcachefs/bcachefs.h
include/benzina/iso/bmff-box.h
include/benzina/iso/bmff-intops.h
include/benzina/iso/bmff-types.h
include/benzina/iso/bmff.h
include/benzina/iso/iso.h
include/benzina/itu/h264.h
include/benzina/itu/h265.h
include/benzina/itu/h26x.h
include/benzina/plugins/nvdecode.h
scripts/LONG_DESCRIPTION.txt
scripts/VERSION.txt
scripts/__init__.py
scripts/bench.py
scripts/detectgpus.c
scripts/elf-strip-df-1-pie.py
scripts/elf.py
scripts/git.py
scripts/import-lua-patches.sh
scripts/lz4-lua-pack.py
scripts/meson.build
scripts/setup.py
scripts/utils.py
scripts/version.py.in
scripts/versioning.py
src/meson.build
src/benzina/__init__.py
src/benzina/native.c
src/benzina/native_datasetcore.c
src/benzina/native_datasetcore.h
src/benzina/native_nvdecodedataloaderitercore.c
src/benzina/native_nvdecodedataloaderitercore.h
src/benzina/native_nvdecodedataloaderitercorebatchcm.c
